MANIFEST.in
RELEASE-VERSION
pavement.py
paver-minilib.zip
setup.py
version.py
git_helpers/__init__.py
git_helpers.egg-info/PKG-INFO
git_helpers.egg-info/SOURCES.txt
git_helpers.egg-info/dependency_links.txt
git_helpers.egg-info/top_level.txt