Metadata-Version: 1.0
Name: git-helpers
Version: 0.2
Summary: Wrapper API around `git` commands.
Home-page: http://github.com/wheeler-microfluidics/git_helpers.git
Author: Christian Fobel
Author-email: christian@fobel.net
License: GPLv2
Platform: UNKNOWN
